{"title":"网易 国内新闻","url":"https://m.163.com/touch/news/sub/domestic","favicon":"https://m.163.com/touch/news/sub/favicon.ico","elements":[{"title":"一家三口遭同村男子持刀砍死 凶手被鉴定为精神分裂","contents":"<a href=\"/news/article/K3574SD8051492T3.html\" class=\"cards-oneImg cards-newsCard\"><article><section class=\"s-left\"><h4>一家三口遭同村男子持刀砍死 凶手被鉴定为精神分裂</h4><div class=\"s-info\"><!----><span class=\"s-source\">红星新闻</span><span class=\"s-replyCount\">123跟贴</span><!----><span class=\"s-holder\"></span><!----></div></section><section class=\"s-right\"><img src=\"https://nimg.ws.126.net/?url=http%3A%2F%2Fdingyue.ws.126.net%2F2025%2F0628%2Ffcf54b37j00syjyc800gnd000tq00eog.jpg&amp;thumbnail=230x2147483647&amp;quality=75&amp;type=webp\" alt=\"一家三口遭同村男子持刀砍死 凶手被鉴定为精神分裂\" class=\"nimg\" data-src=\"https://nimg.ws.126.net/?url=http%3A%2F%2Fdingyue.ws.126.net%2F2025%2F0628%2Ffcf54b37j00syjyc800gnd000tq00eog.jpg&amp;thumbnail=230x2147483647&amp;quality=75&amp;type=webp\" lazy=\"loaded\"><!----></section></article></a>","link":"https://m.163.com/news/article/K3574SD8051492T3.html","retrieved":1751113961348},{"title":"\"错换人生28年案\"养母起诉生母:为何姚策到北京3天离世","contents":"<a href=\"/news/article/K356VP1U0514BE2Q.html\" class=\"cards-oneImg cards-newsCard\"><article><section class=\"s-left\"><h4>\"错换人生28年案\"养母起诉生母:为何姚策到北京3天离世</h4><div class=\"s-info\"><!----><span class=\"s-source\">中国新闻周刊</span><span class=\"s-replyCount\">1403跟贴</span><!----><span class=\"s-holder\"></span><!----></div></section><section class=\"s-right\"><img src=\"https://nimg.ws.126.net/?url=http%3A%2F%2Fcms-bucket.ws.126.net%2F2025%2F0628%2F8c881e24p00syjzvj001cc0009c0070c.png&amp;thumbnail=230x2147483647&amp;quality=75&amp;type=webp\" alt=\"&quot;错换人生28年案&quot;养母起诉生母:为何姚策到北京3天离世\" class=\"nimg\" data-src=\"https://nimg.ws.126.net/?url=http%3A%2F%2Fcms-bucket.ws.126.net%2F2025%2F0628%2F8c881e24p00syjzvj001cc0009c0070c.png&amp;thumbnail=230x2147483647&amp;quality=75&amp;type=webp\" lazy=\"loaded\"><!----></section></article></a>","link":"https://m.163.com/news/article/K356VP1U0514BE2Q.html","retrieved":1751113961351},{"title":"东方航空原董事长刘绍勇接受审查调查","contents":"<a href=\"/news/article/K34TVK7K0001899O.html\" class=\"cards-oneImg cards-newsCard\"><article><section class=\"s-left\"><h4>东方航空原董事长刘绍勇接受审查调查</h4><div class=\"s-info\"><!----><span class=\"s-source\">澎湃新闻</span><span class=\"s-replyCount\">7585跟贴</span><!----><span class=\"s-holder\"></span><!----></div></section><section class=\"s-right\"><img src=\"https://static.ws.126.net/163/frontend/images/2022/bg.png\" alt=\"东方航空原董事长刘绍勇接受审查调查\" class=\"nimg\" data-src=\"https://nimg.ws.126.net/?url=http%3A%2F%2Fcms-bucket.ws.126.net%2F2025%2F0628%2F6f082f0cp00syjrdy0016c0009c0070c.png&amp;thumbnail=230x2147483647&amp;quality=75&amp;type=webp\" lazy=\"loading\"><!----></section></article></a>","link":"https://m.163.com/news/article/K34TVK7K0001899O.html","retrieved":1751113961351},{"title":"女子带罕见病儿子开网约车 有乘客偷偷留下1万元现金","contents":"<a href=\"/news/article/K32U7MEF0514D3UH.html\" class=\"cards-oneImg cards-newsCard\"><article><section class=\"s-left\"><h4>女子带罕见病儿子开网约车 有乘客偷偷留下1万元现金</h4><div class=\"s-info\"><!----><span class=\"s-source\">封面新闻</span><span class=\"s-replyCount\">623跟贴</span><!----><span class=\"s-holder\"></span><!----></div></section><section class=\"s-right\"><img src=\"https://static.ws.126.net/163/frontend/images/2022/bg.png\" alt=\"女子带罕见病儿子开网约车 有乘客偷偷留下1万元现金\" class=\"nimg\" data-src=\"https://nimg.ws.126.net/?url=http%3A%2F%2Fcms-bucket.ws.126.net%2F2025%2F0628%2F44628c4ap00syjqsw0016c0009c0070c.png&amp;thumbnail=230x2147483647&amp;quality=75&amp;type=webp\" lazy=\"loading\"><!----></section></article></a>","link":"https://m.163.com/news/article/K32U7MEF0514D3UH.html","retrieved":1751113961351},{"title":"新规来了：\"被打还手即互殴\"成历史","contents":"<a href=\"/news/article/K34SA9NC0512D3VJ.html\" class=\"cards-oneImg cards-newsCard\"><article><section class=\"s-left\"><h4>新规来了：\"被打还手即互殴\"成历史</h4><div class=\"s-info\"><!----><span class=\"s-source\">新京报</span><span class=\"s-replyCount\">4730跟贴</span><!----><span class=\"s-holder\"></span><!----></div></section><section class=\"s-right\"><img src=\"https://static.ws.126.net/163/frontend/images/2022/bg.png\" alt=\"新规来了：&quot;被打还手即互殴&quot;成历史\" class=\"nimg\" data-src=\"https://nimg.ws.126.net/?url=http%3A%2F%2Fcms-bucket.ws.126.net%2F2025%2F0628%2F2aed5b26p00syjqxa002ec000er00abc.png&amp;thumbnail=230x2147483647&amp;quality=75&amp;type=webp\" lazy=\"loading\"><!----></section></article></a>","link":"https://m.163.com/news/article/K34SA9NC0512D3VJ.html","retrieved":1751113961351},{"title":"女厅官任上被查 其前任因受贿洗钱于去年3月落马","contents":"<a href=\"/news/article/K34QL07Q0530JPVV.html\" class=\"cards-oneImg cards-newsCard\"><article><section class=\"s-left\"><h4>女厅官任上被查 其前任因受贿洗钱于去年3月落马</h4><div class=\"s-info\"><!----><span class=\"s-source\">鲁中晨报</span><span class=\"s-replyCount\">9跟贴</span><!----><span class=\"s-holder\"></span><!----></div></section><section class=\"s-right\"><img src=\"https://static.ws.126.net/163/frontend/images/2022/bg.png\" alt=\"女厅官任上被查 其前任因受贿洗钱于去年3月落马\" class=\"nimg\" data-src=\"https://nimg.ws.126.net/?url=http%3A%2F%2Fcms-bucket.ws.126.net%2F2025%2F0628%2F7522d471p00syjozu001uc0009c0070c.png&amp;thumbnail=230x2147483647&amp;quality=75&amp;type=webp\" lazy=\"loading\"><!----></section></article></a>","link":"https://m.163.com/news/article/K34QL07Q0530JPVV.html","retrieved":1751091883515},{"title":"老人被毒蛇咬伤病情逐渐恶化 家人艰难决定：放弃治疗","contents":"<a href=\"/news/article/K34NVG0K051492T3.html\" class=\"cards-oneImg cards-newsCard\"><article><section class=\"s-left\"><h4>老人被毒蛇咬伤病情逐渐恶化 家人艰难决定：放弃治疗</h4><div class=\"s-info\"><!----><span class=\"s-source\">红星新闻</span><span class=\"s-replyCount\">5247跟贴</span><!----><span class=\"s-holder\"></span><!----></div></section><section class=\"s-right\"><img src=\"https://static.ws.126.net/163/frontend/images/2022/bg.png\" alt=\"老人被毒蛇咬伤病情逐渐恶化 家人艰难决定：放弃治疗\" class=\"nimg\" data-src=\"https://nimg.ws.126.net/?url=http%3A%2F%2Fcms-bucket.ws.126.net%2F2025%2F0628%2Fdcd0b7bap00syjn9j001bc0009c0070c.png&amp;thumbnail=230x2147483647&amp;quality=75&amp;type=webp\" lazy=\"loading\"><!----></section></article></a>","link":"https://m.163.com/news/article/K34NVG0K051492T3.html","retrieved":1751091883516},{"title":"父亲背了12年的儿子高考624分：将继续背他上大学","contents":"<a href=\"/news/article/K33MHPH70514D3UH.html\" class=\"cards-oneImg cards-newsCard\"><article><section class=\"s-left\"><h4>父亲背了12年的儿子高考624分：将继续背他上大学</h4><div class=\"s-info\"><!----><span class=\"s-source\">封面新闻</span><span class=\"s-replyCount\">298跟贴</span><!----><span class=\"s-holder\"></span><!----></div></section><section class=\"s-right\"><img src=\"https://static.ws.126.net/163/frontend/images/2022/bg.png\" alt=\"父亲背了12年的儿子高考624分：将继续背他上大学\" class=\"nimg\" data-src=\"https://nimg.ws.126.net/?url=http%3A%2F%2Fcms-bucket.ws.126.net%2F2025%2F0628%2Ff9d2ab0ep00syjn110019c0009c0070c.png&amp;thumbnail=230x2147483647&amp;quality=75&amp;type=webp\" lazy=\"loading\"><!----></section></article></a>","link":"https://m.163.com/news/article/K33MHPH70514D3UH.html","retrieved":1751091883517},{"title":"两干部同日被查 其中一人8年前被记过处分","contents":"<a href=\"/news/article/K34MHI9S0530JPVV.html\" class=\"cards-oneImg cards-newsCard\"><article><section class=\"s-left\"><h4>两干部同日被查 其中一人8年前被记过处分</h4><div class=\"s-info\"><!----><span class=\"s-source\">鲁中晨报</span><span class=\"s-replyCount\">26跟贴</span><!----><span class=\"s-holder\"></span><!----></div></section><section class=\"s-right\"><img src=\"https://static.ws.126.net/163/frontend/images/2022/bg.png\" alt=\"两干部同日被查 其中一人8年前被记过处分\" class=\"nimg\" data-src=\"https://nimg.ws.126.net/?url=http%3A%2F%2Fcms-bucket.ws.126.net%2F2025%2F0628%2F6061729fp00syjmmg0016c0009c0070c.png&amp;thumbnail=230x2147483647&amp;quality=75&amp;type=webp\" lazy=\"loading\"><!----></section></article></a>","link":"https://m.163.com/news/article/K34MHI9S0530JPVV.html","retrieved":1751091883518},{"title":"小米YU7爆火 首批车主欲出租新车一天租金1.5万元","contents":"<a href=\"/news/article/K34M6VBR0514R9P4.html\" class=\"cards-oneImg cards-newsCard\"><article><section class=\"s-left\"><h4>小米YU7爆火 首批车主欲出租新车一天租金1.5万元</h4><div class=\"s-info\"><!----><span class=\"s-source\">澎湃新闻</span><span class=\"s-replyCount\">1892跟贴</span><!----><span class=\"s-holder\"></span><!----></div></section><section class=\"s-right\"><img src=\"https://static.ws.126.net/163/frontend/images/2022/bg.png\" alt=\"小米YU7爆火 首批车主欲出租新车一天租金1.5万元\" class=\"nimg\" data-src=\"https://nimg.ws.126.net/?url=http%3A%2F%2Fdingyue.ws.126.net%2F2025%2F0628%2Ffa62e1bcj00syjkyp0028d000sr00g6c.jpg&amp;thumbnail=230x2147483647&amp;quality=75&amp;type=webp\" lazy=\"loading\"><!----></section></article></a>","link":"https://m.163.com/news/article/K34M6VBR0514R9P4.html","retrieved":1751091883520},{"title":"外媒纷纷点赞小米YU7：特斯拉迎来最强挑战者","contents":"<a href=\"/news/article/K337SA2605504DPG.html\" class=\"cards-oneImg cards-newsCard\"><article><section class=\"s-left\"><h4>外媒纷纷点赞小米YU7：特斯拉迎来最强挑战者</h4><div class=\"s-info\"><!----><span class=\"s-source\">环球时报新闻</span><span class=\"s-replyCount\">9630跟贴</span><!----><span class=\"s-holder\"></span><!----></div></section><section class=\"s-right\"><img src=\"https://static.ws.126.net/163/frontend/images/2022/bg.png\" alt=\"外媒纷纷点赞小米YU7：特斯拉迎来最强挑战者\" class=\"nimg\" data-src=\"https://nimg.ws.126.net/?url=http%3A%2F%2Fcms-bucket.ws.126.net%2F2025%2F0628%2Fd312d17ep00syjfse004sc0009c0070c.png&amp;thumbnail=230x2147483647&amp;quality=75&amp;type=webp\" lazy=\"loading\"><!----></section></article></a>","link":"https://m.163.com/news/article/K337SA2605504DPG.html","retrieved":1751091883522},{"title":"炮轰小米YU7粉丝\"愚忠\" 东风日产高管发文道歉","contents":"<a href=\"/news/article/K34H1T5N0530JPVV.html\" class=\"cards-oneImg cards-newsCard\"><article><section class=\"s-left\"><h4>炮轰小米YU7粉丝\"愚忠\" 东风日产高管发文道歉</h4><div class=\"s-info\"><!----><span class=\"s-source\">鲁中晨报</span><span class=\"s-replyCount\">407跟贴</span><!----><span class=\"s-holder\"></span><!----></div></section><section class=\"s-right\"><img src=\"https://static.ws.126.net/163/frontend/images/2022/bg.png\" alt=\"炮轰小米YU7粉丝&quot;愚忠&quot; 东风日产高管发文道歉\" class=\"nimg\" data-src=\"https://nimg.ws.126.net/?url=http%3A%2F%2Fcms-bucket.ws.126.net%2F2025%2F0628%2F747d9a36p00syjkea0013c0009c0070c.png&amp;thumbnail=230x2147483647&amp;quality=75&amp;type=webp\" lazy=\"loading\"><!----></section></article></a>","link":"https://m.163.com/news/article/K34H1T5N0530JPVV.html","retrieved":1751091883523},{"title":"\"9·3\"大阅兵多兵种将首次亮相 网友期待看\"机器狼群\"","contents":"<a href=\"/news/article/K34DNP700514R9OJ.html\" class=\"cards-oneImg cards-newsCard\"><article><section class=\"s-left\"><h4>\"9·3\"大阅兵多兵种将首次亮相 网友期待看\"机器狼群\"</h4><div class=\"s-info\"><!----><span class=\"s-source\">环球网资讯</span><span class=\"s-replyCount\">39跟贴</span><!----><span class=\"s-holder\"></span><!----></div></section><section class=\"s-right\"><img src=\"https://static.ws.126.net/163/frontend/images/2022/bg.png\" alt=\"&quot;9·3&quot;大阅兵多兵种将首次亮相 网友期待看&quot;机器狼群&quot;\" class=\"nimg\" data-src=\"https://nimg.ws.126.net/?url=http%3A%2F%2Fcms-bucket.ws.126.net%2F2025%2F0628%2Fc5ad72a1p00syjjf1004ic0009c0070c.png&amp;thumbnail=230x2147483647&amp;quality=75&amp;type=webp\" lazy=\"loading\"><!----></section></article></a>","link":"https://m.163.com/news/article/K34DNP700514R9OJ.html","retrieved":1751091883529},{"title":"食品添加剂使用情况专项抽检结果发布，滥用问题仍突出","contents":"<a href=\"/news/article/K338VFLG0534A4SC.html\" class=\"cards-oneImg cards-newsCard\"><article><section class=\"s-left\"><h4>食品添加剂使用情况专项抽检结果发布，滥用问题仍突出</h4><div class=\"s-info\"><!----><span class=\"s-source\">界面新闻</span><span class=\"s-replyCount\">555跟贴</span><!----><span class=\"s-holder\"></span><!----></div></section><section class=\"s-right\"><img src=\"https://static.ws.126.net/163/frontend/images/2022/bg.png\" alt=\"食品添加剂使用情况专项抽检结果发布，滥用问题仍突出\" class=\"nimg\" data-src=\"https://nimg.ws.126.net/?url=http%3A%2F%2Fdingyue.ws.126.net%2F2025%2F0627%2Fa4ed1540j00syikd8001zd0009c005uc.jpg&amp;thumbnail=230x2147483647&amp;quality=75&amp;type=webp\" lazy=\"loading\"><!----></section></article></a>","link":"https://m.163.com/news/article/K338VFLG0534A4SC.html","retrieved":1751091883531},{"title":"深交所：拟将主板风险警示股票价格的涨跌幅限制比例调整为10%","contents":"<a href=\"/news/article/K32R643I0534A4SC.html\" class=\"cards-oneImg cards-newsCard\"><article><section class=\"s-left\"><h4>深交所：拟将主板风险警示股票价格的涨跌幅限制比例调整为10%</h4><div class=\"s-info\"><!----><span class=\"s-source\">界面新闻</span><span class=\"s-replyCount\">2977跟贴</span><!----><span class=\"s-holder\"></span><!----></div></section><section class=\"s-right\"><img src=\"https://static.ws.126.net/163/frontend/images/2022/bg.png\" alt=\"深交所：拟将主板风险警示股票价格的涨跌幅限制比例调整为10%\" class=\"nimg\" data-src=\"https://nimg.ws.126.net/?url=http%3A%2F%2Fdingyue.ws.126.net%2F2025%2F0627%2F28726db3j00syi97h0009d0009c005uc.jpg&amp;thumbnail=230x2147483647&amp;quality=75&amp;type=webp\" lazy=\"loading\"><!----></section></article></a>","link":"https://m.163.com/news/article/K32R643I0534A4SC.html","retrieved":1751027945510},{"title":"王化回应网传\"小米前总监\"大瓜：该人曾入职小米食堂","contents":"<a href=\"/news/article/K32LOG6R0530JPVV.html\" class=\"cards-oneImg cards-newsCard\"><article><section class=\"s-left\"><h4>王化回应网传\"小米前总监\"大瓜：该人曾入职小米食堂</h4><div class=\"s-info\"><!----><span class=\"s-source\">鲁中晨报</span><span class=\"s-replyCount\">20跟贴</span><!----><span class=\"s-holder\"></span><!----></div></section><section class=\"s-right\"><img src=\"https://static.ws.126.net/163/frontend/images/2022/bg.png\" alt=\"王化回应网传&quot;小米前总监&quot;大瓜：该人曾入职小米食堂\" class=\"nimg\" data-src=\"https://nimg.ws.126.net/?url=http%3A%2F%2Fcms-bucket.ws.126.net%2F2025%2F0627%2F8e3d9d45p00syi62j000zc0009c0070c.png&amp;thumbnail=230x2147483647&amp;quality=75&amp;type=webp\" lazy=\"loading\"><!----></section></article></a>","link":"https://m.163.com/news/article/K32LOG6R0530JPVV.html","retrieved":1751027945515},{"title":"商务部：美方将取消对华一系列限制性措施","contents":"<a href=\"/news/article/K32MM4Q00001899O.html\" class=\"cards-oneImg cards-newsCard\"><article><section class=\"s-left\"><h4>商务部：美方将取消对华一系列限制性措施</h4><div class=\"s-info\"><!----><span class=\"s-source\">日月谭天</span><span class=\"s-replyCount\">2819跟贴</span><!----><span class=\"s-holder\"></span><!----></div></section><section class=\"s-right\"><img src=\"https://static.ws.126.net/163/frontend/images/2022/bg.png\" alt=\"商务部：美方将取消对华一系列限制性措施\" class=\"nimg\" data-src=\"https://nimg.ws.126.net/?url=http%3A%2F%2Fcms-bucket.ws.126.net%2F2025%2F0627%2F3f6d3bbcp00syi6f2001zc0009c0070c.png&amp;thumbnail=230x2147483647&amp;quality=75&amp;type=webp\" lazy=\"loading\"><!----></section></article></a>","link":"https://m.163.com/news/article/K32MM4Q00001899O.html","retrieved":1751027945515},{"title":"女子通过跨省转运治疗重获生机：9小时从江西驶向上海","contents":"<a href=\"/news/article/K311MFHU05345ARG.html\" class=\"cards-oneImg cards-newsCard\"><article><section class=\"s-left\"><h4>女子通过跨省转运治疗重获生机：9小时从江西驶向上海</h4><div class=\"s-info\"><!----><span class=\"s-source\">扬子晚报</span><span class=\"s-replyCount\">295跟贴</span><!----><span class=\"s-holder\"></span><!----></div></section><section class=\"s-right\"><img src=\"https://static.ws.126.net/163/frontend/images/2022/bg.png\" alt=\"女子通过跨省转运治疗重获生机：9小时从江西驶向上海\" class=\"nimg\" data-src=\"https://nimg.ws.126.net/?url=http%3A%2F%2Fcms-bucket.ws.126.net%2F2025%2F0627%2F0b6e08e0p00syi5rs0017c0009c0070c.png&amp;thumbnail=230x2147483647&amp;quality=75&amp;type=webp\" lazy=\"loading\"><!----></section></article></a>","link":"https://m.163.com/news/article/K311MFHU05345ARG.html","retrieved":1751027945515},{"title":"\"网红律师\"西绿被发现涉嫌刑事犯罪 律所称已主动报案","contents":"<a href=\"/news/article/K30VIH9B05561G0D.html\" class=\"cards-oneImg cards-newsCard\"><article><section class=\"s-left\"><h4>\"网红律师\"西绿被发现涉嫌刑事犯罪 律所称已主动报案</h4><div class=\"s-info\"><!----><span class=\"s-source\">大风新闻</span><span class=\"s-replyCount\">385跟贴</span><!----><span class=\"s-holder\"></span><!----></div></section><section class=\"s-right\"><img src=\"https://static.ws.126.net/163/frontend/images/2022/bg.png\" alt=\"&quot;网红律师&quot;西绿被发现涉嫌刑事犯罪 律所称已主动报案\" class=\"nimg\" data-src=\"https://nimg.ws.126.net/?url=http%3A%2F%2Fcms-bucket.ws.126.net%2F2025%2F0627%2Fc15f46d8p00syi4wz002tc0009c0070c.png&amp;thumbnail=230x2147483647&amp;quality=75&amp;type=webp\" lazy=\"loading\"><!----></section></article></a>","link":"https://m.163.com/news/article/K30VIH9B05561G0D.html","retrieved":1751027945516},{"title":"高速断桥货车司机悬空 过路司机出手：说话止不住颤抖","contents":"<a href=\"/news/article/K30RI9VQ0514D3UH.html\" class=\"cards-oneImg cards-newsCard\"><article><section class=\"s-left\"><h4>高速断桥货车司机悬空 过路司机出手：说话止不住颤抖</h4><div class=\"s-info\"><!----><span class=\"s-source\">封面新闻</span><span class=\"s-replyCount\">274跟贴</span><!----><span class=\"s-holder\"></span><!----></div></section><section class=\"s-right\"><img src=\"https://static.ws.126.net/163/frontend/images/2022/bg.png\" alt=\"高速断桥货车司机悬空 过路司机出手：说话止不住颤抖\" class=\"nimg\" data-src=\"https://nimg.ws.126.net/?url=http%3A%2F%2Fcms-bucket.ws.126.net%2F2025%2F0627%2F9e8b6419p00syi4n5003vc0009c0070c.png&amp;thumbnail=230x2147483647&amp;quality=75&amp;type=webp\" lazy=\"loading\"><!----></section></article></a>","link":"https://m.163.com/news/article/K30RI9VQ0514D3UH.html","retrieved":1751005833074},{"title":"男子外出打工失联29年 80岁母亲苦盼儿归：就想见一面","contents":"<a href=\"/news/article/K30K2ML7051492T3.html\" class=\"cards-oneImg cards-newsCard\"><article><section class=\"s-left\"><h4>男子外出打工失联29年 80岁母亲苦盼儿归：就想见一面</h4><div class=\"s-info\"><!----><span class=\"s-source\">红星新闻</span><span class=\"s-replyCount\">1464跟贴</span><!----><span class=\"s-holder\"></span><!----></div></section><section class=\"s-right\"><img src=\"https://static.ws.126.net/163/frontend/images/2022/bg.png\" alt=\"男子外出打工失联29年 80岁母亲苦盼儿归：就想见一面\" class=\"nimg\" data-src=\"https://nimg.ws.126.net/?url=http%3A%2F%2Fcms-bucket.ws.126.net%2F2025%2F0627%2F25dae1b4p00syi3hr0096c0009c0070c.png&amp;thumbnail=230x2147483647&amp;quality=75&amp;type=webp\" lazy=\"loading\"><!----></section></article></a>","link":"https://m.163.com/news/article/K30K2ML7051492T3.html","retrieved":1751005833057},{"title":"前员工偷拍6岁女孩照片用作背景图 西贝发布致歉声明","contents":"<a href=\"/news/article/K32GP87C0001899O.html\" class=\"cards-oneImg cards-newsCard\"><article><section class=\"s-left\"><h4>前员工偷拍6岁女孩照片用作背景图 西贝发布致歉声明</h4><div class=\"s-info\"><!----><span class=\"s-source\">澎湃新闻</span><span class=\"s-replyCount\">2682跟贴</span><!----><span class=\"s-holder\"></span><!----></div></section><section class=\"s-right\"><img src=\"https://static.ws.126.net/163/frontend/images/2022/bg.png\" alt=\"前员工偷拍6岁女孩照片用作背景图 西贝发布致歉声明\" class=\"nimg\" data-src=\"https://nimg.ws.126.net/?url=http%3A%2F%2Fcms-bucket.ws.126.net%2F2025%2F0627%2F613ac33fp00syi2870015c0009c0070c.png&amp;thumbnail=230x2147483647&amp;quality=75&amp;type=webp\" lazy=\"loading\"><!----></section></article></a>","link":"https://m.163.com/news/article/K32GP87C0001899O.html","retrieved":1751005833057},{"title":"治安管理处罚法修订完成 未成年人行拘执行条件有调整","contents":"<a href=\"/news/article/K32CPDD0000189PS.html\" class=\"cards-oneImg cards-newsCard\"><article><section class=\"s-left\"><h4>治安管理处罚法修订完成 未成年人行拘执行条件有调整</h4><div class=\"s-info\"><!----><span class=\"s-source\">央视新闻</span><span class=\"s-replyCount\">2085跟贴</span><!----><span class=\"s-holder\"></span><!----></div></section><section class=\"s-right\"><img src=\"https://static.ws.126.net/163/frontend/images/2022/bg.png\" alt=\"治安管理处罚法修订完成 未成年人行拘执行条件有调整\" class=\"nimg\" data-src=\"https://nimg.ws.126.net/?url=http%3A%2F%2Fcms-bucket.ws.126.net%2F2025%2F0627%2F6479f6c0j00syhy2w000nc000ic00bzc.jpg&amp;thumbnail=230x2147483647&amp;quality=75&amp;type=webp\" lazy=\"loading\"><!----></section></article></a>","link":"https://m.163.com/news/article/K32CPDD0000189PS.html","retrieved":1751005833057},{"title":"吉大学生因宿舍太热支帐篷过夜 校方称暂时无法装空调","contents":"<a href=\"/news/article/K30Q6S420512D3VJ.html\" class=\"cards-oneImg cards-newsCard\"><article><section class=\"s-left\"><h4>吉大学生因宿舍太热支帐篷过夜 校方称暂时无法装空调</h4><div class=\"s-info\"><!----><span class=\"s-source\">新京报</span><span class=\"s-replyCount\">2.0万跟贴</span><!----><span class=\"s-holder\"></span><!----></div></section><section class=\"s-right\"><img src=\"https://static.ws.126.net/163/frontend/images/2022/bg.png\" alt=\"吉大学生因宿舍太热支帐篷过夜 校方称暂时无法装空调\" class=\"nimg\" data-src=\"https://nimg.ws.126.net/?url=http%3A%2F%2Fcms-bucket.ws.126.net%2F2025%2F0627%2Ff42a8429p00syhsn800bjc0009c0070c.png&amp;thumbnail=230x2147483647&amp;quality=75&amp;type=webp\" lazy=\"loading\"><!----></section></article></a>","link":"https://m.163.com/news/article/K30Q6S420512D3VJ.html","retrieved":1751005833057},{"title":"工人发视频称施工现场的螺纹钢一掰就断 当地称不属实","contents":"<a href=\"/news/article/K315K0K3053469LG.html\" class=\"cards-oneImg cards-newsCard\"><article><section class=\"s-left\"><h4>工人发视频称施工现场的螺纹钢一掰就断 当地称不属实</h4><div class=\"s-info\"><!----><span class=\"s-source\">极目新闻</span><span class=\"s-replyCount\">2760跟贴</span><!----><span class=\"s-holder\"></span><!----></div></section><section class=\"s-right\"><img src=\"https://static.ws.126.net/163/frontend/images/2022/bg.png\" alt=\"工人发视频称施工现场的螺纹钢一掰就断 当地称不属实\" class=\"nimg\" data-src=\"https://nimg.ws.126.net/?url=http%3A%2F%2Fcms-bucket.ws.126.net%2F2025%2F0627%2F73a333ffp00syhs8u001oc0009c0070c.png&amp;thumbnail=230x2147483647&amp;quality=75&amp;type=webp\" lazy=\"loading\"><!----></section></article></a>","link":"https://m.163.com/news/article/K315K0K3053469LG.html","retrieved":1751005833058},{"title":"雷军：小米不是靠营销赢的 在绝大部分领域小米都领先","contents":"<a href=\"/news/article/K31DOMT40512B07B.html\" class=\"cards-oneImg cards-newsCard\"><article><section class=\"s-left\"><h4>雷军：小米不是靠营销赢的 在绝大部分领域小米都领先</h4><div class=\"s-info\"><!----><span class=\"s-source\">每日经济新闻</span><span class=\"s-replyCount\">1.8万跟贴</span><!----><span class=\"s-holder\"></span><!----></div></section><section class=\"s-right\"><img src=\"https://static.ws.126.net/163/frontend/images/2022/bg.png\" alt=\"雷军：小米不是靠营销赢的 在绝大部分领域小米都领先\" class=\"nimg\" data-src=\"https://nimg.ws.126.net/?url=http%3A%2F%2Fcms-bucket.ws.126.net%2F2025%2F0627%2F33f4ad6ap00syhroz0013c0009c0070c.png&amp;thumbnail=230x2147483647&amp;quality=75&amp;type=webp\" lazy=\"loading\"><!----></section></article></a>","link":"https://m.163.com/news/article/K31DOMT40512B07B.html","retrieved":1751005833059},{"title":"有机场已提前执行民航局新规定 网友：成筐充电宝被拦","contents":"<a href=\"/news/article/K31TR78T055040N3.html\" class=\"cards-oneImg cards-newsCard\"><article><section class=\"s-left\"><h4>有机场已提前执行民航局新规定 网友：成筐充电宝被拦</h4><div class=\"s-info\"><!----><span class=\"s-source\">上观新闻</span><span class=\"s-replyCount\">2.2万跟贴</span><!----><span class=\"s-holder\"></span><!----></div></section><section class=\"s-right\"><img src=\"https://static.ws.126.net/163/frontend/images/2022/bg.png\" alt=\"有机场已提前执行民航局新规定 网友：成筐充电宝被拦\" class=\"nimg\" data-src=\"https://nimg.ws.126.net/?url=http%3A%2F%2Fcms-bucket.ws.126.net%2F2025%2F0627%2F8b487ea1p00syhqfq001uc0009c0070c.png&amp;thumbnail=230x2147483647&amp;quality=75&amp;type=webp\" lazy=\"loading\"><!----></section></article></a>","link":"https://m.163.com/news/article/K31TR78T055040N3.html","retrieved":1751005833065},{"title":"溢价率达379.6% 河北网红公司1.1亿深圳\"抢楼\"后悔拍","contents":"<a href=\"/news/article/K320DPLT0512B07B.html\" class=\"cards-oneImg cards-newsCard\"><article><section class=\"s-left\"><h4>溢价率达379.6% 河北网红公司1.1亿深圳\"抢楼\"后悔拍</h4><div class=\"s-info\"><!----><span class=\"s-source\">每日经济新闻</span><span class=\"s-replyCount\">3885跟贴</span><!----><span class=\"s-holder\"></span><!----></div></section><section class=\"s-right\"><img src=\"https://static.ws.126.net/163/frontend/images/2022/bg.png\" alt=\"溢价率达379.6% 河北网红公司1.1亿深圳&quot;抢楼&quot;后悔拍\" class=\"nimg\" data-src=\"https://nimg.ws.126.net/?url=http%3A%2F%2Fdingyue.ws.126.net%2F2025%2F0627%2F37f33566j00syhncb0036d000u000m6g.jpg&amp;thumbnail=230x2147483647&amp;quality=75&amp;type=webp\" lazy=\"loading\"><!----></section></article></a>","link":"https://m.163.com/news/article/K320DPLT0512B07B.html","retrieved":1750987427401},{"title":"75万采购防火墙实为普通路由器 近2个月后校方再回应","contents":"<a href=\"/news/article/K311CQA6053469LG.html\" class=\"cards-oneImg cards-newsCard\"><article><section class=\"s-left\"><h4>75万采购防火墙实为普通路由器 近2个月后校方再回应</h4><div class=\"s-info\"><!----><span class=\"s-source\">极目新闻</span><span class=\"s-replyCount\">1.0万跟贴</span><!----><span class=\"s-holder\"></span><!----></div></section><section class=\"s-right\"><img src=\"https://static.ws.126.net/163/frontend/images/2022/bg.png\" alt=\"75万采购防火墙实为普通路由器 近2个月后校方再回应\" class=\"nimg\" data-src=\"https://nimg.ws.126.net/?url=http%3A%2F%2Fcms-bucket.ws.126.net%2F2025%2F0627%2F3b858b0ap00syhlwu001sc0009c0070c.png&amp;thumbnail=230x2147483647&amp;quality=75&amp;type=webp\" lazy=\"loading\"><!----></section></article></a>","link":"https://m.163.com/news/article/K311CQA6053469LG.html","retrieved":1750987427408},{"title":"隐居深山10年后61岁韦唯重返舞台：我险些失去了生命","contents":"<a href=\"/news/article/K31SMPG6055040N3.html\" class=\"cards-oneImg cards-newsCard\"><article><section class=\"s-left\"><h4>隐居深山10年后61岁韦唯重返舞台：我险些失去了生命</h4><div class=\"s-info\"><!----><span class=\"s-source\">上观新闻</span><span class=\"s-replyCount\">846跟贴</span><!----><span class=\"s-holder\"></span><!----></div></section><section class=\"s-right\"><img src=\"https://static.ws.126.net/163/frontend/images/2022/bg.png\" alt=\"隐居深山10年后61岁韦唯重返舞台：我险些失去了生命\" class=\"nimg\" data-src=\"https://nimg.ws.126.net/?url=http%3A%2F%2Fcms-bucket.ws.126.net%2F2025%2F0627%2F820f7b2cp00syhl6y0010c0009c0070c.png&amp;thumbnail=230x2147483647&amp;quality=75&amp;type=webp\" lazy=\"loading\"><!----></section></article></a>","link":"https://m.163.com/news/article/K31SMPG6055040N3.html","retrieved":1750987427409}]}