{"title":"重庆市国有资产监督管理委员会","url":"https://gzw.cq.gov.cn/gqzp/","favicon":"https://gzw.cq.gov.cn/gqzp/favicon.ico","elements":[{"contents":"<a href=\"./202506/t20250620_14732096.html\" target=\"_blank\" aria-arttitle=\"true\" aria-width=\"0\" aria-height=\"0\">重庆市纪委监委驻西南证券公司纪检监察组关于公开遴选及选聘工作人员的公告</a> <span aria-arttime=\"true\" aria-width=\"0\" aria-height=\"0\">2025-06-20</span>","retrieved":1750789626396},{"contents":"<a href=\"./202506/t20250620_14732093.html\" target=\"_blank\" aria-arttitle=\"true\" aria-width=\"0\" aria-height=\"0\">重庆市工程管理有限公司招聘公告</a> <span aria-arttime=\"true\" aria-width=\"0\" aria-height=\"0\">2025-06-20</span>","retrieved":1750789626396},{"contents":"<a href=\"./202506/t20250620_14732091.html\" target=\"_blank\" aria-arttitle=\"true\" aria-width=\"0\" aria-height=\"0\">重庆市轨道交通设计研究院有限责任公司博士后研究人员招聘公告</a> <span aria-arttime=\"true\" aria-width=\"0\" aria-height=\"0\">2025-06-20</span>","retrieved":1750789626398},{"contents":"<a href=\"./202506/t20250620_14732087.html\" target=\"_blank\" aria-arttitle=\"true\" aria-width=\"0\" aria-height=\"0\">关于延长重庆市水产科学研究所社会招聘报名时间的公告</a> <span aria-arttime=\"true\" aria-width=\"0\" aria-height=\"0\">2025-06-20</span>","retrieved":1750789626399},{"contents":"<a href=\"./202506/t20250620_14732086.html\" target=\"_blank\" aria-arttitle=\"true\" aria-width=\"0\" aria-height=\"0\">重庆新华出版集团招聘公告</a> <span aria-arttime=\"true\" aria-width=\"0\" aria-height=\"0\">2025-06-20</span>","retrieved":1750789626400},{"contents":"<a href=\"./202506/t20250620_14732084.html\" target=\"_blank\" aria-arttitle=\"true\" aria-width=\"0\" aria-height=\"0\">重庆物流集团渝地绿能科技有限公司招聘公告</a> <span aria-arttime=\"true\" aria-width=\"0\" aria-height=\"0\">2025-06-20</span>","retrieved":1750789626402},{"contents":"<a href=\"./202506/t20250620_14732066.html\" target=\"_blank\" aria-arttitle=\"true\" aria-width=\"0\" aria-height=\"0\">重庆轮船（集团）有限公司交运游轮分公司招聘公告</a> <span aria-arttime=\"true\" aria-width=\"0\" aria-height=\"0\">2025-06-20</span>","retrieved":1750789626403},{"contents":"<a href=\"./202506/t20250620_14732062.html\" target=\"_blank\" aria-arttitle=\"true\" aria-width=\"0\" aria-height=\"0\">重庆蓝盾电子技术有限责任公司招聘简章</a> <span aria-arttime=\"true\" aria-width=\"0\" aria-height=\"0\">2025-06-20</span>","retrieved":1750789626405},{"contents":"<a href=\"./202506/t20250620_14732060.html\" target=\"_blank\" aria-arttitle=\"true\" aria-width=\"0\" aria-height=\"0\">重庆金迪汽车零部件有限公司招聘公告</a> <span aria-arttime=\"true\" aria-width=\"0\" aria-height=\"0\">2025-06-20</span>","retrieved":1750789626406},{"contents":"<a href=\"./202506/t20250620_14732055.html\" target=\"_blank\" aria-arttitle=\"true\" aria-width=\"0\" aria-height=\"0\">重庆机电控股集团资产管理有限公司通用能源科技分公司招聘公告</a> <span aria-arttime=\"true\" aria-width=\"0\" aria-height=\"0\">2025-06-20</span>","retrieved":1750789626407},{"contents":"<a href=\"./202506/t20250620_14732052.html\" target=\"_blank\" aria-arttitle=\"true\" aria-width=\"0\" aria-height=\"0\">重庆登康口腔健康科技有限公司招聘公告</a> <span aria-arttime=\"true\" aria-width=\"0\" aria-height=\"0\">2025-06-20</span>","retrieved":1750789626409},{"contents":"<a href=\"./202506/t20250620_14732050.html\" target=\"_blank\" aria-arttitle=\"true\" aria-width=\"0\" aria-height=\"0\">【校招】重庆登康口腔护理用品股份有限公司招聘公告</a> <span aria-arttime=\"true\" aria-width=\"0\" aria-height=\"0\">2025-06-20</span>","retrieved":1750789626410},{"contents":"<a href=\"./202506/t20250620_14732045.html\" target=\"_blank\" aria-arttitle=\"true\" aria-width=\"0\" aria-height=\"0\">重庆登康口腔护理用品股份有限公司招聘公告</a> <span aria-arttime=\"true\" aria-width=\"0\" aria-height=\"0\">2025-06-20</span>","retrieved":1750789626411},{"contents":"<a href=\"./202506/t20250620_14732044.html\" target=\"_blank\" aria-arttitle=\"true\" aria-width=\"0\" aria-height=\"0\">【校招】重庆成飞新材料股份公司招聘公告</a> <span aria-arttime=\"true\" aria-width=\"0\" aria-height=\"0\">2025-06-20</span>","retrieved":1750789626413},{"contents":"<a href=\"./202506/t20250620_14732041.html\" target=\"_blank\" aria-arttitle=\"true\" aria-width=\"0\" aria-height=\"0\">重庆成飞新材料股份公司招聘公告</a> <span aria-arttime=\"true\" aria-width=\"0\" aria-height=\"0\">2025-06-20</span>","retrieved":1750789626414}]}